{
    "key": "group_5f4ab83050560",
    "title": "Buttons Petition Template",
    "fields": [
        {
            "key": "field_5f4ab8596aef1",
            "label": "Button 1",
            "name": "petition_btn1",
            "type": "link",
            "instructions": "",
            "required": 1,
            "conditional_logic": 0,
            "wrapper": {
                "width": "",
                "class": "",
                "id": ""
            },
            "return_format": "array"
        },
        {
            "key": "field_5f4ab86b6aef2",
            "label": "Button 2",
            "name": "petition_btn2",
            "type": "link",
            "instructions": "",
            "required": 1,
            "conditional_logic": 0,
            "wrapper": {
                "width": "",
                "class": "",
                "id": ""
            },
            "return_format": "array"
        },
        {
            "key": "field_5f4b617d4c284",
            "label": "Bild",
            "name": "petition_image",
            "type": "image",
            "instructions": "",
            "required": 1,
            "conditional_logic": 0,
            "wrapper": {
                "width": "",
                "class": "",
                "id": ""
            },
            "return_format": "array",
            "preview_size": "medium",
            "library": "all",
            "min_width": "",
            "min_height": "",
            "min_size": "",
            "max_width": "",
            "max_height": "",
            "max_size": "",
            "mime_types": ""
        }
    ],
    "location": [
        [
            {
                "param": "page_template",
                "operator": "==",
                "value": "template-petition.php"
            }
        ]
    ],
    "menu_order": 0,
    "position": "normal",
    "style": "default",
    "label_placement": "top",
    "instruction_placement": "label",
    "hide_on_screen": "",
    "active": true,
    "description": "",
    "modified": 1598775690
}